ftn/__init__.py
ftn-0.9.19.dist-info/LICENSE.txt
ftn-0.9.19.dist-info/METADATA
ftn-0.9.19.dist-info/WHEEL
ftn-0.9.19.dist-info/top_level.txt
ftn-0.9.19.dist-info/RECORD
