Metadata-Version: 2.1
Name: ftn
Version: 0.9.19
Summary: A module to connect to Fotonower' services
Home-page: https://github.com/fotonower/fotonowerpip
Author: The Python Packaging Authority
Author-email: victor@fotonower.com
License: UNKNOWN
Project-URL: Funding, https://donate.pypi.org
Project-URL: Bug Reports, https://github.com/pypa/sampleproject/issues
Project-URL: Say Thanks!, http://saythanks.io/to/example
Project-URL: Source, https://github.com/pypa/sampleproject/
Keywords: setuptools development
Platform: UNKNOWN
Classifier: Development Status :: 3 - Alpha
Classifier: Intended Audience :: Developers
Classifier: Topic :: Software Development :: Build Tools
Classifier: License :: OSI Approved :: MIT License
Classifier: Programming Language :: Python :: 2.7
Classifier: Programming Language :: Python :: 3.4
Classifier: Programming Language :: Python :: 3.5
Classifier: Programming Language :: Python :: 3.6
Requires-Dist: requests
